tapas/__init__.py
tapas/create_pretrain_examples_main.py
tapas/run_task_main.py
tapas/datasets/__init__.py
tapas/datasets/dataset.py
tapas/datasets/dataset_test.py
tapas/datasets/table_dataset.py
tapas/datasets/table_dataset_test.py
tapas/datasets/table_dataset_test_utils.py
tapas/experiments/__init__.py
tapas/experiments/prediction_utils.py
tapas/experiments/prediction_utils_test.py
tapas/experiments/tapas_classifier_experiment.py
tapas/experiments/tapas_pretraining_experiment.py
tapas/models/__init__.py
tapas/models/segmented_tensor.py
tapas/models/segmented_tensor_test.py
tapas/models/tapas_classifier_model.py
tapas/models/tapas_classifier_model_test.py
tapas/models/tapas_classifier_model_utils.py
tapas/models/tapas_pretraining_model.py
tapas/models/tapas_pretraining_model_test.py
tapas/models/bert/__init__.py
tapas/models/bert/modeling.py
tapas/models/bert/modeling_test.py
tapas/models/bert/optimization.py
tapas/models/bert/optimization_test.py
tapas/models/bert/table_bert.py
tapas/protos/__init__.py
tapas/protos/interaction_pb2.py
tapas/protos/table_selection_pb2.py
tapas/scripts/__init__.py
tapas/scripts/calc_metrics.py
tapas/scripts/calc_metrics_test.py
tapas/scripts/calc_metrics_utils.py
tapas/scripts/convert_predictions.py
tapas/scripts/convert_predictions_utils.py
tapas/scripts/convert_predictions_utils_test.py
tapas/scripts/eval_wikisql.py
tapas/scripts/prediction_utils.py
tapas/scripts/prediction_utils_test.py
tapas/utils/__init__.py
tapas/utils/beam_runner.py
tapas/utils/constants.py
tapas/utils/experiment_utils.py
tapas/utils/experiment_utils_test.py
tapas/utils/file_utils.py
tapas/utils/hparam_utils.py
tapas/utils/interaction_utils.py
tapas/utils/interaction_utils_parser.py
tapas/utils/interaction_utils_parser_test.py
tapas/utils/interaction_utils_test.py
tapas/utils/interpretation_utils.py
tapas/utils/interpretation_utils_test.py
tapas/utils/number_annotation_utils.py
tapas/utils/number_annotation_utils_test.py
tapas/utils/number_utils.py
tapas_table_parsing-0.0.1.dev0.dist-info/AUTHORS
tapas_table_parsing-0.0.1.dev0.dist-info/LICENSE
tapas_table_parsing-0.0.1.dev0.dist-info/METADATA
tapas_table_parsing-0.0.1.dev0.dist-info/WHEEL
tapas_table_parsing-0.0.1.dev0.dist-info/top_level.txt
tapas_table_parsing-0.0.1.dev0.dist-info/RECORD
