Metadata-Version: 2.1
Name: tapas-table-parsing
Version: 0.0.1.dev0
Summary: Tapas: Table-based Question Answering.
Home-page: https://github.com/google-research/tapas
Author: Google Inc.
License: Apache 2.0
Platform: UNKNOWN
Requires-Dist: apache-beam[gcp] (==2.20.0)
Requires-Dist: frozendict (==1.2)
Requires-Dist: pandas (~=1.0.0)
Requires-Dist: scikit-learn (~=0.22.1)
Requires-Dist: tensorflow (~=2.2.0)
Requires-Dist: tf-models-official (~=2.2.0)
Requires-Dist: kaggle (<1.5.8)
Requires-Dist: tensorflow-probability (==0.10.1)
Requires-Dist: tf-slim (~=1.1.0)
Requires-Dist: nltk (~=3.5)
Requires-Dist: dataclasses (~=0.7) ; python_version < "3.7"
